simple_interval/__init__.py
simple_interval/simple_interval.py
simple_interval-0.1.5.dist-info/licenses/LICENSE
simple_interval-0.1.5.dist-info/METADATA
simple_interval-0.1.5.dist-info/WHEEL
simple_interval-0.1.5.dist-info/top_level.txt
simple_interval-0.1.5.dist-info/RECORD
