Metadata-Version: 2.4
Name: simple-interval
Version: 0.1.5
Summary: Using Python threading to run a function at a specific interval. This implementation is very similar to the implemention of threading.Timer in Python - just runs on an interval instead of single time.
Author-email: Heath Henley <heath.j.henley@gmail.com>
License-Expression: MIT
Project-URL: Homepage, https://github.com/heathhenley/simple-interval
Project-URL: Repository, https://github.com/heathhenley/simple-interval
Project-URL: Issues, https://github.com/heathhenley/simple-interval/issues
Requires-Python: >=3.12
License-File: LICENSE
Dynamic: license-file
